CHANGELOG.md
LICENSE
MANIFEST.in
README.md
requirements-dev.txt
requirements-test.txt
requirements.txt
setup.cfg
setup.py
flaskmogrify/__init__.py
flaskmogrify/forms.py
flaskmogrify.egg-info/PKG-INFO
flaskmogrify.egg-info/SOURCES.txt
flaskmogrify.egg-info/dependency_links.txt
flaskmogrify.egg-info/not-zip-safe
flaskmogrify.egg-info/requires.txt
flaskmogrify.egg-info/top_level.txt
flaskmogrify/static/jquery-3.2.1.js
flaskmogrify/static/jquery-3.2.1.min.js
flaskmogrify/static/style.css
flaskmogrify/templates/base.html
flaskmogrify/templates/results_non_AJAX.html
flaskmogrify/templates/transmogrify.html