Metadata-Version: 1.1
Name: flaskmogrify
Version: 0.0.16
Summary: Flaskmogrify, a simple Flask single pageapplication to convert (w/ Ajax) user-pasted text using an arbitrary text conversion function.
Home-page: https://github.com/danyul/flaskmogrify
Author: Daniel Langsam
Author-email: daniel@langsam.org
License: MIT
Keywords: flask convert text transform ajax single page application
Platform: UNKNOWN
Classifier: Natural Language :: English
Classifier: Programming Language :: Python :: 3.6
